sparkly/__init__.py
sparkly/analysis.py
sparkly/index_config.py
sparkly/search.py
sparkly/utils.py
sparkly/index/__init__.py
sparkly/index/index_base.py
sparkly/index/lucene_index.py
sparkly/index_optimizer/__init__.py
sparkly/index_optimizer/index_optimizer.py
sparkly/index_optimizer/query_scorer.py
sparkly/query_generator/__init__.py
sparkly/query_generator/lucene_query_generator.py
sparkly/query_generator/lucene_weighted_query_generator.py
sparkly/query_generator/query_spec.py
sparkly_em-0.1.0.dist-info/METADATA
sparkly_em-0.1.0.dist-info/WHEEL
sparkly_em-0.1.0.dist-info/licenses/LICENSE
sparkly_em-0.1.0.dist-info/RECORD
