Metadata-Version: 2.3
Name: sparkly-em
Version: 0.1.0
Summary: Sparkly is a TF/IDF top-k blocking for entity matching system built on top of Apache Spark and PyLucene.
Author-email: Derek Paulsen <derekpaulsensi@gmail.com>
License:                                  Apache License
License-File: LICENSE
Keywords: Lucene,PyLucene,Spark,distributed,entity matching,entity resolution,matching
Classifier: Development Status :: 4 - Beta
Classifier: Intended Audience :: Developers
Classifier: License :: OSI Approved :: Apache Software License
Classifier: Programming Language :: Python :: 3
Classifier: Programming Language :: Python :: 3.8
Classifier: Programming Language :: Python :: 3.9
Classifier: Programming Language :: Python :: 3.10
Requires-Python: >=3.8
Requires-Dist: joblib>=1.2.0
Requires-Dist: mmh3>=3.0.0
Requires-Dist: numba>=0.58.0
Requires-Dist: numpy>=1.21.5
Requires-Dist: numpydoc>=1.5.0
Requires-Dist: pandas>=1.5.2
Requires-Dist: psutil>=5.9.0
Requires-Dist: pyarrow>=10.0.1
Requires-Dist: pydantic>=2.6.0
Requires-Dist: pyspark>=3.3.1
Requires-Dist: scipy>=1.8.0
Requires-Dist: tqdm>=4.64.1
